Workbook

Sheet Leia-me
A1: Calculadora de retorno — loja de lavanderia self-service
A2: Planilha de apoio à decisão. Os valores iniciais são os da calculadora de referência; troque pelos seus.
A4: Como usar
A5: 1. Em Investimento, informe os equipamentos (bocas, cestos por boca, preço, quantidade) e os itens de obra e instalação.
A6: 2. Em Premissas, ajuste operação, receita, custos, impostos e forma de pagamento.
A7: 3. Em Resultados, veja investimento, margem, payback, ROI e os três cenários. O fluxo mês a mês está em Fluxo.
A9: Cores
A10: Azul: valor que você edita. Preto: fórmula. Verde: valor trazido de outra aba. Fundo amarelo: premissa que mais pesa no resultado.
A12: Como o cálculo funciona
A13: Cesto: unidade de volume e de cobrança. Cada boca (de lavagem ou de secagem) processa alguns cestos por ciclo.
A14: Cestos de lavagem por dia = cestos de base × ciclos por boca, arredondado para cima. Na secagem, multiplica-se também pela utilização da secagem.
A15: Receita mensal = (cestos lavados + cestos secos por dia) × preço por cesto × dias de operação.
... A28: Projeção não garante resultado. Valide as premissas com a operação real e com o seu fornecedor antes de decidir.

Sheet Investimento
A1: Investimento
A2: Equipamentos e infraestrutura. Valores iniciais iguais aos da calculadora de referência.
A4: Equipamento | B4: Bocas de lavagem | C4: Bocas de secagem | D4: Cestos por boca | E4: Preço unitário (R$) | F4: Quantidade | G4: Subtotal (R$) | H4: Cestos de lavagem (base) | I4: Cestos de secagem (base) | J4: Bocas de lavagem (total) | K4: Bocas de secagem (total)
A5: Chassi pequeno 2 × 10 kg | B5: 1 | C5: 1 | D5: 1 | E5: 37234 | F5: 3 | G5: =E5*F5 -> 111702 | H5: =F5*B5*D5 -> 3 | I5: =F5*C5*D5 -> 3 | J5: =F5*B5 -> 3 | K5: =F5*C5 -> 3
A6: Chassi grande 30, 2 × 13,6 kg | B6: 1 | C6: 1 | D6: 2 | E6: 72616 | F6: 2 | G6: =E6*F6 -> 145232 | H6: =F6*B6*D6 -> 4 | I6: =F6*C6*D6 -> 4 | J6: =F6*B6 -> 2 | K6: =F6*C6 -> 2
A7: Chassi grande 50, 2 × 22,7 kg | B7: 1 | C7: 1 | D7: 3 | E7: 88723 | F7: 0 | G7: =E7*F7 -> 0 | H7: =F7*B7*D7 -> 0 | I7: =F7*C7*D7 -> 0 | J7: =F7*B7 -> 0 | K7: =F7*C7 -> 0
A8: Lavadora-extratora 20 kg + secadora | B8: 1 | C8: 1 | D8: 3 | E8: 90014 | F8: 0 | G8: =E8*F8 -> 0 | H8: =F8*B8*D8 -> 0 | I8: =F8*C8*D8 -> 0 | J8: =F8*B8 -> 0 | K8: =F8*C8 -> 0
A9: Outro equipamento 1 | B9: 0 | C9: 0 | D9: 0 | E9: 0 | F9: 0 | G9: =E9*F9 -> 0 | H9: =F9*B9*D9 -> 0 | I9: =F9*C9*D9 -> 0 | J9: =F9*B9 -> 0 | K9: =F9*C9 -> 0
A10: Outro equipamento 2 | B10: 0 | C10: 0 | D10: 0 | E10: 0 | F10: 0 | G10: =E10*F10 -> 0 | H10: =F10*B10*D10 -> 0 | I10: =F10*C10*D10 -> 0 | J10: =F10*B10 -> 0 | K10: =F10*C10 -> 0
A11: Outro equipamento 3 | B11: 0 | C11: 0 | D11: 0 | E11: 0 | F11: 0 | G11: =E11*F11 -> 0 | H11: =F11*B11*D11 -> 0 | I11: =F11*C11*D11 -> 0 | J11: =F11*B11 -> 0 | K11: =F11*C11 -> 0
A12: Outro equipamento 4 | B12: 0 | C12: 0 | D12: 0 | E12: 0 | F12: 0 | G12: =E12*F12 -> 0 | H12: =F12*B12*D12 -> 0 | I12: =F12*C12*D12 -> 0 | J12: =F12*B12 -> 0 | K12: =F12*C12 -> 0
A13: Total | F13: =SUM(F5:F12) -> 5 | G13: =SUM(G5:G12) -> 256934 | H13: =SUM(H5:H12) -> 7 | I13: =SUM(I5:I12) -> 7 | J13: =SUM(J5:J12) -> 5 | K13: =SUM(K5:K12) -> 5
A14: Torre lava-e-seca = 1 boca de lavagem + 1 de secagem. Lavadora sozinha: lavagem 1, secagem 0. Secadora sozinha: lavagem 0, secagem 1.
A16: Infraestrutura e instalação
A17: Item | B17: Tipo | C17: Valor (R$) | D17: Custo considerado (R$)
A18: Projeto da loja | B18: Fixo | C18: 5000 | D18: =IF(B18="Por máquina",C18*$F$13,C18) -> 5000
A19: Parede + porta de vidro | B19: Fixo | C19: 3000 | D19: =IF(B19="Por máquina",C19*$F$13,C19) -> 3000
A20: Ar-condicionado (c/ instalação) | B20: Fixo | C20: 3500 | D20: =IF(B20="Por máquina",C20*$F$13,C20) -> 3500
A21: Drywall | B21: Fixo | C21: 3000 | D21: =IF(B21="Por máquina",C21*$F$13,C21) -> 3000
A22: M.O. pintura + material | B22: Fixo | C22: 2500 | D22: =IF(B22="Por máquina",C22*$F$13,C22) -> 2500
A23: Adesivagem interna | B23: Fixo | C23: 1500 | D23: =IF(B23="Por máquina",C23*$F$13,C23) -> 1500
A24: Diversos (alarme, internet, etc.) | B24: Fixo | C24: 1500 | D24: =IF(B24="Por máquina",C24*$F$13,C24) -> 1500
A25: Sistema (maquininha) | B25: Fixo | C25: 4000 | D25: =IF(B25="Por máquina",C25*$F$13,C25) -> 4000
A26: Caixa d’água 600L | B26: Fixo | C26: 900 | D26: =IF(B26="Por máquina",C26*$F$13,C26) -> 900
A27: Bomba pressurização (1CV) | B27: Fixo | C27: 1300 | D27: =IF(B27="Por máquina",C27*$F$13,C27) -> 1300
A28: Acessórios e periféricos | B28: Fixo | C28: 600 | D28: =IF(B28="Por máquina",C28*$F$13,C28) -> 600
A29: Mesa de dobra | B29: Fixo | C29: 600 | D29: =IF(B29="Por máquina",C29*$F$13,C29) -> 600
... A40: 1ª compra de químicos | B40: Por máquina | C40: 300 | D40: =IF(B40="Por máquina",C40*$F$13,C40) -> 1500
A41: Total da infraestrutura | D41: =ROUND(SUM(D18:D40),0) -> 43480
A42: Fixo: valor total, independe da quantidade. Por máquina: valor por unidade de equipamento, multiplicado pela quantidade total (célula F13). O total é arredondado em reais inteiros.

Sheet Premissas
A1: Premissas
A2: Valores iniciais iguais aos da calculadora de referência. Troque pelos dados da sua operação.
A3: Operação e receita
A4: Ciclos por boca por dia (loja madura) | B4: 6 | C4: Quantas vezes cada boca roda por dia. Premissa de maior impacto.
A5: Utilização da secagem (%) | B5: 100 | C5: Ritmo da secagem em relação à lavagem. Pode passar de 100% (ex.: 120% em clima úmido).
A6: Preço por cesto (R$) | B6: 18 | C6: Cobrado por cesto, em cada operação (lavagem e secagem contam separadas).
A7: Dias de operação por mês | B7: 30
A8: Utilização inicial, loja nova (%) | B8: 45 | C8: Utilização no mês 1, como fração da capacidade madura.
A9: Meses até a maturidade | B9: 12 | C9: Mês em que a loja chega a 100% da capacidade.
A11: Custos
A12: Custo variável de lavagem (R$ por cesto) | B12: 4.5 | C12: Energia, água e químicos consumidos por cesto lavado.
A13: Custo variável de secagem (R$ por cesto) | B13: 2.16 | C13: Energia ou gás consumidos por cesto seco.
A14: Impostos sobre a receita (%) | B14: 10 | C14: Descontado da receita. Ajuste ao seu regime tributário.
A15: Horizonte de análise (anos, de 1 a 50) | B15: 5
A17: Custo fixo mensal
A18: Aluguel | B18: 3500 | C18: Energia e água das máquinas entram no custo variável por cesto. Não repita aqui.
A19: Energia — base/área comum (sem máquinas) | B19: 1200
A20: Água — base/limpeza (sem máquinas) | B20: 400
A21: Internet + sistema | B21: 300
A22: Mão de obra / limpeza | B22: 2000
A23: Diversos | B23: 600
A24: Total do custo fixo mensal | B24: =ROUND(SUM(B18:B23),0) -> 8000 | C24: Arredondado em reais inteiros. Para usar outro valor, digite por cima desta fórmula.
A26: Pagamento do investimento
A27: Forma de pagamento | B27: À vista | C27: Escolha À vista ou Financiado. Entrada, prazo e taxa só valem no financiamento.
A28: Entrada (% do investimento) | B28: 20
A29: Prazo (meses) | B29: 24 | C29: Parcelas fixas (tabela Price).
A30: Taxa de juros (%) | B30: 2
A31: Unidade da taxa | B31: ao mês
A32: Taxa mensal efetiva | B32: =IF(B31="ao ano",(1+B30/100)^(1/12)-1,B30/100) -> 0.02

Sheet Resultados
A1: Resultados
A2: Tudo nesta aba é calculado. Edite apenas as abas Investimento e Premissas.
A3: Investimento e pagamento
A4: Equipamentos | B4: =Investimento!G13 -> 256934
A5: Infraestrutura | B5: =Investimento!D41 -> 43480
A6: Investimento total | B6: =B4+B5 -> 300414
A7: Desembolso inicial (entrada) | B7: =IF(Premissas!B27="Financiado",B6*(MIN(100,MAX(0,Premissas!B28))/100),B6) -> 300414
A8: Valor financiado | B8: =B6-B7 -> 0
A9: Número de parcelas | B9: =IF(Premissas!B27="Financiado",MAX(1,ROUND(Premissas!B29,0)),0) -> 0
A10: Parcela mensal | B10: =IF(B9=0,0,IF(Premissas!B32>0,B8*Premissas!B32/(1-(1+Premissas!B32)^(-B9)),B8/B9)) -> 0
A11: Juros totais do financiamento | B11: =B10*B9-B8 -> 0
A13: Operação na maturidade (cenário realista)
A14: Cestos de lavagem por dia | B14: =ROUNDUP(Investimento!H13*Premissas!B4,0) -> 42
A15: Cestos de secagem por dia | B15: =ROUNDUP(Investimento!I13*(Premissas!B5/100)*Premissas!B4,0) -> 42
A16: Cestos por dia | B16: =B14+B15 -> 84
A17: Bocas (lavagem + secagem) | B17: =Investimento!J13+Investimento!K13 -> 10
A18: Ciclos de máquina por dia | B18: =ROUND(Investimento!J13*Premissas!B4+Investimento!K13*Premissas!B4*(Premissas!B5/100),0) -> 60
A19: Receita mensal plena | B19: =B16*Premissas!B6*Premissas!B7 -> 45360
A20: Custo variável mensal | B20: =(Premissas!B12*B14+Premissas!B13*B15)*Premissas!B7 -> 8391.6
A21: Custo fixo mensal | B21: =Premissas!B24 -> 8000
A22: Impostos sobre a receita | B22: =B19*(Premissas!B14/100) -> 4536
A23: Margem mensal plena | B23: =B19-B20-B21-B22 -> 24432.4
A24: Custo operacional pleno (variável + fixo) | B24: =B20+B21 -> 16391.6
A26: Indicadores
A27: Payback simples (meses) | B27: =IF(B23>0,B6/B23,"—") -> 12.295722
A28: ROI anual | B28: =IF(B23>0,IF(B6>0,B23*12/B6,0),"—") -> 0.97594919
A29: Payback com rampa (meses) | B29: =IF(COUNT(Fluxo!S5:S604)=0,"—",MIN(Fluxo!S5:S604)) -> 16.676254
A30: Lucro líquido acumulado no horizonte | B30: =INDEX(Fluxo!R4:R604,ROUNDDOWN(Premissas!B15*12,0)+1) -> 1058503.1 | C30: Já descontados impostos, entrada, parcelas e juros.
A31: Receita no mês 1 (com rampa) | B31: =B19*Fluxo!B5 -> 20412
A32: Receita no ano 1 (com rampa) | B32: =SUMPRODUCT(Fluxo!B5:B16*B19) -> 394632
A33: Receita no ano 1 na maturidade | B33: =B19*12 -> 544320
A35: Cenários de rotatividade
A36: Cenário | B36: Ciclos por boca por dia | C36: Cestos de lavagem por dia | D36: Cestos de secagem por dia | E36: Receita mensal plena | F36: Custo variável mensal | G36: Margem mensal plena | H36: Payback com rampa (meses)
A37: Conservador | B37: =MAX(1,Premissas!B4-1) -> 5 | C37: =ROUNDUP(Investimento!$H$13*B37,0) -> 35 | D37: =ROUNDUP(Investimento!$I$13*(Premissas!$B$5/100)*B37,0) -> 35 | E37: =(C37+D37)*Premissas!$B$6*Premissas!$B$7 -> 37800 | F37: =(Premissas!$B$12*C37+Premissas!$B$13*D37)*Premissas!$B$7 -> 6993 | G37: =E37-F37-Premissas!$B$24-E37*(Premissas!$B$14/100) -> 19027 | H37: =IF(COUNT(Fluxo!G5:G604)=0,"—",MIN(Fluxo!G5:G604)) -> 20.476328
A38: Realista | B38: =MAX(1,Premissas!B4) -> 6 | C38: =ROUNDUP(Investimento!$H$13*B38,0) -> 42 | D38: =ROUNDUP(Investimento!$I$13*(Premissas!$B$5/100)*B38,0) -> 42 | E38: =(C38+D38)*Premissas!$B$6*Premissas!$B$7 -> 45360 | F38: =(Premissas!$B$12*C38+Premissas!$B$13*D38)*Premissas!$B$7 -> 8391.6 | G38: =E38-F38-Premissas!$B$24-E38*(Premissas!$B$14/100) -> 24432.4 | H38: =IF(COUNT(Fluxo!K5:K604)=0,"—",MIN(Fluxo!K5:K604)) -> 16.676254
A39: Otimista | B39: =MAX(1,Premissas!B4+1) -> 7 | C39: =ROUNDUP(Investimento!$H$13*B39,0) -> 49 | D39: =ROUNDUP(Investimento!$I$13*(Premissas!$B$5/100)*B39,0) -> 49 | E39: =(C39+D39)*Premissas!$B$6*Premissas!$B$7 -> 52920 | F39: =(Premissas!$B$12*C39+Premissas!$B$13*D39)*Premissas!$B$7 -> 9790.2 | G39: =E39-F39-Premissas!$B$24-E39*(Premissas!$B$14/100) -> 29837.8 | H39: =IF(COUNT(Fluxo!O5:O604)=0,"—",MIN(Fluxo!O5:O604)) -> 14.253019
A40: “—” em payback significa que o caixa não cruza zero no prazo analisado (120 meses ou o horizonte, o que for maior).

Sheet Fluxo
A1: Fluxo de caixa mensal
A2: Caixa acumulado por cenário. O mês 0 é a entrada (desembolso inicial). A última coluna usa os ciclos informados, sem o mínimo de 1.
A3: Mês | B3: Utilização | C3: Parcela | D3: Margem (conserv.) | E3: Fluxo (conserv.) | F3: Acumulado (conserv.) | G3: Cruzamento (conserv.) | H3: Margem (realista) | I3: Fluxo (realista) | J3: Acumulado (realista) | K3: Cruzamento (realista) | L3: Margem (otimista) | M3: Fluxo (otimista) | N3: Acumulado (otimista) | O3: Cruzamento (otimista) | P3: Margem (indicadores) | Q3: Fluxo (indicadores) | R3: Acumulado (indicadores) | S3: Cruzamento (indicadores)
A4: 0 | F4: =-Resultados!$B$7 -> -300414 | J4: =-Resultados!$B$7 -> -300414 | N4: =-Resultados!$B$7 -> -300414 | R4: =-Resultados!$B$7 -> -300414
A5: =A4+1 -> 1 | B5: =IF(Premissas!$B$9<=1,1,MIN(1,Premissas!$B$8/100+(1-Premissas!$B$8/100)*(A5-1)/(Premissas!$B$9-1))) -> 0.45 | C5: =IF(A5<=Resultados!$B$9,Resultados!$B$10,0) -> 0 | D5: =Resultados!$E$37*$B5-Resultados!$F$37*$B5-Premissas!$B$24-Resultados!$E$37*$B5*(Premissas!$B$14/100) -> 4162.15 | E5: =D5-$C5 -> 4162.15 | F5: =F4+E5 -> -296251.85 | G5: =IF(AND(F4<0,F5>=0,A5<=MAX(120,Premissas!$B$15*12)),(A5-1)+(-F4)/E5,"") | H5: =Resultados!$E$38*$B5-Resultados!$F$38*$B5-Premissas!$B$24-Resultados!$E$38*$B5*(Premissas!$B$14/100) -> 6594.58 | I5: =H5-$C5 -> 6594.58 | J5: =J4+I5 -> -293819.42 | K5: =IF(AND(J4<0,J5>=0,A5<=MAX(120,Premissas!$B$15*12)),(A5-1)+(-J4)/I5,"") | L5: =Resultados!$E$39*$B5-Resultados!$F$39*$B5-Premissas!$B$24-Resultados!$E$39*$B5*(Premissas!$B$14/100) -> 9027.01 | M5: =L5-$C5 -> 9027.01 | N5: =N4+M5 -> -291386.99 | O5: =IF(AND(N4<0,N5>=0,A5<=MAX(120,Premissas!$B$15*12)),(A5-1)+(-N4)/M5,"") | P5: =Resultados!$B$19*$B5-Resultados!$B$20*$B5-Premissas!$B$24-Resultados!$B$19*$B5*(Premissas!$B$14/100) -> 6594.58 | Q5: =P5-$C5 -> 6594.58 | R5: =R4+Q5 -> -293819.42 | S5: =IF(AND(R4<0,R5>=0,A5<=MAX(120,Premissas!$B$15*12)),(A5-1)+(-R4)/Q5,"")
A6: =A5+1 -> 2 | B6: =IF(Premissas!$B$9<=1,1,MIN(1,Premissas!$B$8/100+(1-Premissas!$B$8/100)*(A6-1)/(Premissas!$B$9-1))) -> 0.5 | C6: =IF(A6<=Resultados!$B$9,Resultados!$B$10,0) -> 0 | D6: =Resultados!$E$37*$B6-Resultados!$F$37*$B6-Premissas!$B$24-Resultados!$E$37*$B6*(Premissas!$B$14/100) -> 5513.5 | E6: =D6-$C6 -> 5513.5 | F6: =F5+E6 -> -290738.35 | G6: =IF(AND(F5<0,F6>=0,A6<=MAX(120,Premissas!$B$15*12)),(A6-1)+(-F5)/E6,"") | H6: =Resultados!$E$38*$B6-Resultados!$F$38*$B6-Premissas!$B$24-Resultados!$E$38*$B6*(Premissas!$B$14/100) -> 8216.2 | I6: =H6-$C6 -> 8216.2 | J6: =J5+I6 -> -285603.22 | K6: =IF(AND(J5<0,J6>=0,A6<=MAX(120,Premissas!$B$15*12)),(A6-1)+(-J5)/I6,"") | L6: =Resultados!$E$39*$B6-Resultados!$F$39*$B6-Premissas!$B$24-Resultados!$E$39*$B6*(Premissas!$B$14/100) -> 10918.9 | M6: =L6-$C6 -> 10918.9 | N6: =N5+M6 -> -280468.09 | O6: =IF(AND(N5<0,N6>=0,A6<=MAX(120,Premissas!$B$15*12)),(A6-1)+(-N5)/M6,"") | P6: =Resultados!$B$19*$B6-Resultados!$B$20*$B6-Premissas!$B$24-Resultados!$B$19*$B6*(Premissas!$B$14/100) -> 8216.2 | Q6: =P6-$C6 -> 8216.2 | R6: =R5+Q6 -> -285603.22 | S6: =IF(AND(R5<0,R6>=0,A6<=MAX(120,Premissas!$B$15*12)),(A6-1)+(-R5)/Q6,"")
A7: =A6+1 -> 3 | B7: =IF(Premissas!$B$9<=1,1,MIN(1,Premissas!$B$8/100+(1-Premissas!$B$8/100)*(A7-1)/(Premissas!$B$9-1))) -> 0.55 | C7: =IF(A7<=Resultados!$B$9,Resultados!$B$10,0) -> 0 | D7: =Resultados!$E$37*$B7-Resultados!$F$37*$B7-Premissas!$B$24-Resultados!$E$37*$B7*(Premissas!$B$14/100) -> 6864.85 | E7: =D7-$C7 -> 6864.85 | F7: =F6+E7 -> -283873.5 | G7: =IF(AND(F6<0,F7>=0,A7<=MAX(120,Premissas!$B$15*12)),(A7-1)+(-F6)/E7,"") | H7: =Resultados!$E$38*$B7-Resultados!$F$38*$B7-Premissas!$B$24-Resultados!$E$38*$B7*(Premissas!$B$14/100) -> 9837.82 | I7: =H7-$C7 -> 9837.82 | J7: =J6+I7 -> -275765.4 | K7: =IF(AND(J6<0,J7>=0,A7<=MAX(120,Premissas!$B$15*12)),(A7-1)+(-J6)/I7,"") | L7: =Resultados!$E$39*$B7-Resultados!$F$39*$B7-Premissas!$B$24-Resultados!$E$39*$B7*(Premissas!$B$14/100) -> 12810.79 | M7: =L7-$C7 -> 12810.79 | N7: =N6+M7 -> -267657.3 | O7: =IF(AND(N6<0,N7>=0,A7<=MAX(120,Premissas!$B$15*12)),(A7-1)+(-N6)/M7,"") | P7: =Resultados!$B$19*$B7-Resultados!$B$20*$B7-Premissas!$B$24-Resultados!$B$19*$B7*(Premissas!$B$14/100) -> 9837.82 | Q7: =P7-$C7 -> 9837.82 | R7: =R6+Q7 -> -275765.4 | S7: =IF(AND(R6<0,R7>=0,A7<=MAX(120,Premissas!$B$15*12)),(A7-1)+(-R6)/Q7,"")
A8: =A7+1 -> 4 | B8: =IF(Premissas!$B$9<=1,1,MIN(1,Premissas!$B$8/100+(1-Premissas!$B$8/100)*(A8-1)/(Premissas!$B$9-1))) -> 0.6 | C8: =IF(A8<=Resultados!$B$9,Resultados!$B$10,0) -> 0 | D8: =Resultados!$E$37*$B8-Resultados!$F$37*$B8-Premissas!$B$24-Resultados!$E$37*$B8*(Premissas!$B$14/100) -> 8216.2 | E8: =D8-$C8 -> 8216.2 | F8: =F7+E8 -> -275657.3 | G8: =IF(AND(F7<0,F8>=0,A8<=MAX(120,Premissas!$B$15*12)),(A8-1)+(-F7)/E8,"") | H8: =Resultados!$E$38*$B8-Resultados!$F$38*$B8-Premissas!$B$24-Resultados!$E$38*$B8*(Premissas!$B$14/100) -> 11459.44 | I8: =H8-$C8 -> 11459.44 | J8: =J7+I8 -> -264305.96 | K8: =IF(AND(J7<0,J8>=0,A8<=MAX(120,Premissas!$B$15*12)),(A8-1)+(-J7)/I8,"") | L8: =Resultados!$E$39*$B8-Resultados!$F$39*$B8-Premissas!$B$24-Resultados!$E$39*$B8*(Premissas!$B$14/100) -> 14702.68 | M8: =L8-$C8 -> 14702.68 | N8: =N7+M8 -> -252954.62 | O8: =IF(AND(N7<0,N8>=0,A8<=MAX(120,Premissas!$B$15*12)),(A8-1)+(-N7)/M8,"") | P8: =Resultados!$B$19*$B8-Resultados!$B$20*$B8-Premissas!$B$24-Resultados!$B$19*$B8*(Premissas!$B$14/100) -> 11459.44 | Q8: =P8-$C8 -> 11459.44 | R8: =R7+Q8 -> -264305.96 | S8: =IF(AND(R7<0,R8>=0,A8<=MAX(120,Premissas!$B$15*12)),(A8-1)+(-R7)/Q8,"")
A9: =A8+1 -> 5 | B9: =IF(Premissas!$B$9<=1,1,MIN(1,Premissas!$B$8/100+(1-Premissas!$B$8/100)*(A9-1)/(Premissas!$B$9-1))) -> 0.65 | C9: =IF(A9<=Resultados!$B$9,Resultados!$B$10,0) -> 0 | D9: =Resultados!$E$37*$B9-Resultados!$F$37*$B9-Premissas!$B$24-Resultados!$E$37*$B9*(Premissas!$B$14/100) -> 9567.55 | E9: =D9-$C9 -> 9567.55 | F9: =F8+E9 -> -266089.75 | G9: =IF(AND(F8<0,F9>=0,A9<=MAX(120,Premissas!$B$15*12)),(A9-1)+(-F8)/E9,"") | H9: =Resultados!$E$38*$B9-Resultados!$F$38*$B9-Premissas!$B$24-Resultados!$E$38*$B9*(Premissas!$B$14/100) -> 13081.06 | I9: =H9-$C9 -> 13081.06 | J9: =J8+I9 -> -251224.9 | K9: =IF(AND(J8<0,J9>=0,A9<=MAX(120,Premissas!$B$15*12)),(A9-1)+(-J8)/I9,"") | L9: =Resultados!$E$39*$B9-Resultados!$F$39*$B9-Premissas!$B$24-Resultados!$E$39*$B9*(Premissas!$B$14/100) -> 16594.57 | M9: =L9-$C9 -> 16594.57 | N9: =N8+M9 -> -236360.05 | O9: =IF(AND(N8<0,N9>=0,A9<=MAX(120,Premissas!$B$15*12)),(A9-1)+(-N8)/M9,"") | P9: =Resultados!$B$19*$B9-Resultados!$B$20*$B9-Premissas!$B$24-Resultados!$B$19*$B9*(Premissas!$B$14/100) -> 13081.06 | Q9: =P9-$C9 -> 13081.06 | R9: =R8+Q9 -> -251224.9 | S9: =IF(AND(R8<0,R9>=0,A9<=MAX(120,Premissas!$B$15*12)),(A9-1)+(-R8)/Q9,"")
A10: =A9+1 -> 6 | B10: =IF(Premissas!$B$9<=1,1,MIN(1,Premissas!$B$8/100+(1-Premissas!$B$8/100)*(A10-1)/(Premissas!$B$9-1))) -> 0.7 | C10: =IF(A10<=Resultados!$B$9,Resultados!$B$10,0) -> 0 | D10: =Resultados!$E$37*$B10-Resultados!$F$37*$B10-Premissas!$B$24-Resultados!$E$37*$B10*(Premissas!$B$14/100) -> 10918.9 | E10: =D10-$C10 -> 10918.9 | F10: =F9+E10 -> -255170.85 | G10: =IF(AND(F9<0,F10>=0,A10<=MAX(120,Premissas!$B$15*12)),(A10-1)+(-F9)/E10,"") | H10: =Resultados!$E$38*$B10-Resultados!$F$38*$B10-Premissas!$B$24-Resultados!$E$38*$B10*(Premissas!$B$14/100) -> 14702.68 | I10: =H10-$C10 -> 14702.68 | J10: =J9+I10 -> -236522.22 | K10: =IF(AND(J9<0,J10>=0,A10<=MAX(120,Premissas!$B$15*12)),(A10-1)+(-J9)/I10,"") | L10: =Resultados!$E$39*$B10-Resultados!$F$39*$B10-Premissas!$B$24-Resultados!$E$39*$B10*(Premissas!$B$14/100) -> 18486.46 | M10: =L10-$C10 -> 18486.46 | N10: =N9+M10 -> -217873.59 | O10: =IF(AND(N9<0,N10>=0,A10<=MAX(120,Premissas!$B$15*12)),(A10-1)+(-N9)/M10,"") | P10: =Resultados!$B$19*$B10-Resultados!$B$20*$B10-Premissas!$B$24-Resultados!$B$19*$B10*(Premissas!$B$14/100) -> 14702.68 | Q10: =P10-$C10 -> 14702.68 | R10: =R9+Q10 -> -236522.22 | S10: =IF(AND(R9<0,R10>=0,A10<=MAX(120,Premissas!$B$15*12)),(A10-1)+(-R9)/Q10,"")
A11: =A10+1 -> 7 | B11: =IF(Premissas!$B$9<=1,1,MIN(1,Premissas!$B$8/100+(1-Premissas!$B$8/100)*(A11-1)/(Premissas!$B$9-1))) -> 0.75 | C11: =IF(A11<=Resultados!$B$9,Resultados!$B$10,0) -> 0 | D11: =Resultados!$E$37*$B11-Resultados!$F$37*$B11-Premissas!$B$24-Resultados!$E$37*$B11*(Premissas!$B$14/100) -> 12270.25 | E11: =D11-$C11 -> 12270.25 | F11: =F10+E11 -> -242900.6 | G11: =IF(AND(F10<0,F11>=0,A11<=MAX(120,Premissas!$B$15*12)),(A11-1)+(-F10)/E11,"") | H11: =Resultados!$E$38*$B11-Resultados!$F$38*$B11-Premissas!$B$24-Resultados!$E$38*$B11*(Premissas!$B$14/100) -> 16324.3 | I11: =H11-$C11 -> 16324.3 | J11: =J10+I11 -> -220197.92 | K11: =IF(AND(J10<0,J11>=0,A11<=MAX(120,Premissas!$B$15*12)),(A11-1)+(-J10)/I11,"") | L11: =Resultados!$E$39*$B11-Resultados!$F$39*$B11-Premissas!$B$24-Resultados!$E$39*$B11*(Premissas!$B$14/100) -> 20378.35 | M11: =L11-$C11 -> 20378.35 | N11: =N10+M11 -> -197495.24 | O11: =IF(AND(N10<0,N11>=0,A11<=MAX(120,Premissas!$B$15*12)),(A11-1)+(-N10)/M11,"") | P11: =Resultados!$B$19*$B11-Resultados!$B$20*$B11-Premissas!$B$24-Resultados!$B$19*$B11*(Premissas!$B$14/100) -> 16324.3 | Q11: =P11-$C11 -> 16324.3 | R11: =R10+Q11 -> -220197.92 | S11: =IF(AND(R10<0,R11>=0,A11<=MAX(120,Premissas!$B$15*12)),(A11-1)+(-R10)/Q11,"")
A12: =A11+1 -> 8 | B12: =IF(Premissas!$B$9<=1,1,MIN(1,Premissas!$B$8/100+(1-Premissas!$B$8/100)*(A12-1)/(Premissas!$B$9-1))) -> 0.8 | C12: =IF(A12<=Resultados!$B$9,Resultados!$B$10,0) -> 0 | D12: =Resultados!$E$37*$B12-Resultados!$F$37*$B12-Premissas!$B$24-Resultados!$E$37*$B12*(Premissas!$B$14/100) -> 13621.6 | E12: =D12-$C12 -> 13621.6 | F12: =F11+E12 -> -229279 | G12: =IF(AND(F11<0,F12>=0,A12<=MAX(120,Premissas!$B$15*12)),(A12-1)+(-F11)/E12,"") | H12: =Resultados!$E$38*$B12-Resultados!$F$38*$B12-Premissas!$B$24-Resultados!$E$38*$B12*(Premissas!$B$14/100) -> 17945.92 | I12: =H12-$C12 -> 17945.92 | J12: =J11+I12 -> -202252 | K12: =IF(AND(J11<0,J12>=0,A12<=MAX(120,Premissas!$B$15*12)),(A12-1)+(-J11)/I12,"") | L12: =Resultados!$E$39*$B12-Resultados!$F$39*$B12-Premissas!$B$24-Resultados!$E$39*$B12*(Premissas!$B$14/100) -> 22270.24 | M12: =L12-$C12 -> 22270.24 | N12: =N11+M12 -> -175225 | O12: =IF(AND(N11<0,N12>=0,A12<=MAX(120,Premissas!$B$15*12)),(A12-1)+(-N11)/M12,"") | P12: =Resultados!$B$19*$B12-Resultados!$B$20*$B12-Premissas!$B$24-Resultados!$B$19*$B12*(Premissas!$B$14/100) -> 17945.92 | Q12: =P12-$C12 -> 17945.92 | R12: =R11+Q12 -> -202252 | S12: =IF(AND(R11<0,R12>=0,A12<=MAX(120,Premissas!$B$15*12)),(A12-1)+(-R11)/Q12,"")
A13: =A12+1 -> 9 | B13: =IF(Premissas!$B$9<=1,1,MIN(1,Premissas!$B$8/100+(1-Premissas!$B$8/100)*(A13-1)/(Premissas!$B$9-1))) -> 0.85 | C13: =IF(A13<=Resultados!$B$9,Resultados!$B$10,0) -> 0 | D13: =Resultados!$E$37*$B13-Resultados!$F$37*$B13-Premissas!$B$24-Resultados!$E$37*$B13*(Premissas!$B$14/100) -> 14972.95 | E13: =D13-$C13 -> 14972.95 | F13: =F12+E13 -> -214306.05 | G13: =IF(AND(F12<0,F13>=0,A13<=MAX(120,Premissas!$B$15*12)),(A13-1)+(-F12)/E13,"") | H13: =Resultados!$E$38*$B13-Resultados!$F$38*$B13-Premissas!$B$24-Resultados!$E$38*$B13*(Premissas!$B$14/100) -> 19567.54 | I13: =H13-$C13 -> 19567.54 | J13: =J12+I13 -> -182684.46 | K13: =IF(AND(J12<0,J13>=0,A13<=MAX(120,Premissas!$B$15*12)),(A13-1)+(-J12)/I13,"") | L13: =Resultados!$E$39*$B13-Resultados!$F$39*$B13-Premissas!$B$24-Resultados!$E$39*$B13*(Premissas!$B$14/100) -> 24162.13 | M13: =L13-$C13 -> 24162.13 | N13: =N12+M13 -> -151062.87 | O13: =IF(AND(N12<0,N13>=0,A13<=MAX(120,Premissas!$B$15*12)),(A13-1)+(-N12)/M13,"") | P13: =Resultados!$B$19*$B13-Resultados!$B$20*$B13-Premissas!$B$24-Resultados!$B$19*$B13*(Premissas!$B$14/100) -> 19567.54 | Q13: =P13-$C13 -> 19567.54 | R13: =R12+Q13 -> -182684.46 | S13: =IF(AND(R12<0,R13>=0,A13<=MAX(120,Premissas!$B$15*12)),(A13-1)+(-R12)/Q13,"")
A14: =A13+1 -> 10 | B14: =IF(Premissas!$B$9<=1,1,MIN(1,Premissas!$B$8/100+(1-Premissas!$B$8/100)*(A14-1)/(Premissas!$B$9-1))) -> 0.9 | C14: =IF(A14<=Resultados!$B$9,Resultados!$B$10,0) -> 0 | D14: =Resultados!$E$37*$B14-Resultados!$F$37*$B14-Premissas!$B$24-Resultados!$E$37*$B14*(Premissas!$B$14/100) -> 16324.3 | E14: =D14-$C14 -> 16324.3 | F14: =F13+E14 -> -197981.75 | G14: =IF(AND(F13<0,F14>=0,A14<=MAX(120,Premissas!$B$15*12)),(A14-1)+(-F13)/E14,"") | H14: =Resultados!$E$38*$B14-Resultados!$F$38*$B14-Premissas!$B$24-Resultados!$E$38*$B14*(Premissas!$B$14/100) -> 21189.16 | I14: =H14-$C14 -> 21189.16 | J14: =J13+I14 -> -161495.3 | K14: =IF(AND(J13<0,J14>=0,A14<=MAX(120,Premissas!$B$15*12)),(A14-1)+(-J13)/I14,"") | L14: =Resultados!$E$39*$B14-Resultados!$F$39*$B14-Premissas!$B$24-Resultados!$E$39*$B14*(Premissas!$B$14/100) -> 26054.02 | M14: =L14-$C14 -> 26054.02 | N14: =N13+M14 -> -125008.85 | O14: =IF(AND(N13<0,N14>=0,A14<=MAX(120,Premissas!$B$15*12)),(A14-1)+(-N13)/M14,"") | P14: =Resultados!$B$19*$B14-Resultados!$B$20*$B14-Premissas!$B$24-Resultados!$B$19*$B14*(Premissas!$B$14/100) -> 21189.16 | Q14: =P14-$C14 -> 21189.16 | R14: =R13+Q14 -> -161495.3 | S14: =IF(AND(R13<0,R14>=0,A14<=MAX(120,Premissas!$B$15*12)),(A14-1)+(-R13)/Q14,"")
A15: =A14+1 -> 11 | B15: =IF(Premissas!$B$9<=1,1,MIN(1,Premissas!$B$8/100+(1-Premissas!$B$8/100)*(A15-1)/(Premissas!$B$9-1))) -> 0.95 | C15: =IF(A15<=Resultados!$B$9,Resultados!$B$10,0) -> 0 | D15: =Resultados!$E$37*$B15-Resultados!$F$37*$B15-Premissas!$B$24-Resultados!$E$37*$B15*(Premissas!$B$14/100) -> 17675.65 | E15: =D15-$C15 -> 17675.65 | F15: =F14+E15 -> -180306.1 | G15: =IF(AND(F14<0,F15>=0,A15<=MAX(120,Premissas!$B$15*12)),(A15-1)+(-F14)/E15,"") | H15: =Resultados!$E$38*$B15-Resultados!$F$38*$B15-Premissas!$B$24-Resultados!$E$38*$B15*(Premissas!$B$14/100) -> 22810.78 | I15: =H15-$C15 -> 22810.78 | J15: =J14+I15 -> -138684.52 | K15: =IF(AND(J14<0,J15>=0,A15<=MAX(120,Premissas!$B$15*12)),(A15-1)+(-J14)/I15,"") | L15: =Resultados!$E$39*$B15-Resultados!$F$39*$B15-Premissas!$B$24-Resultados!$E$39*$B15*(Premissas!$B$14/100) -> 27945.91 | M15: =L15-$C15 -> 27945.91 | N15: =N14+M15 -> -97062.94 | O15: =IF(AND(N14<0,N15>=0,A15<=MAX(120,Premissas!$B$15*12)),(A15-1)+(-N14)/M15,"") | P15: =Resultados!$B$19*$B15-Resultados!$B$20*$B15-Premissas!$B$24-Resultados!$B$19*$B15*(Premissas!$B$14/100) -> 22810.78 | Q15: =P15-$C15 -> 22810.78 | R15: =R14+Q15 -> -138684.52 | S15: =IF(AND(R14<0,R15>=0,A15<=MAX(120,Premissas!$B$15*12)),(A15-1)+(-R14)/Q15,"")
A16: =A15+1 -> 12 | B16: =IF(Premissas!$B$9<=1,1,MIN(1,Premissas!$B$8/100+(1-Premissas!$B$8/100)*(A16-1)/(Premissas!$B$9-1))) -> 1 | C16: =IF(A16<=Resultados!$B$9,Resultados!$B$10,0) -> 0 | D16: =Resultados!$E$37*$B16-Resultados!$F$37*$B16-Premissas!$B$24-Resultados!$E$37*$B16*(Premissas!$B$14/100) -> 19027 | E16: =D16-$C16 -> 19027 | F16: =F15+E16 -> -161279.1 | G16: =IF(AND(F15<0,F16>=0,A16<=MAX(120,Premissas!$B$15*12)),(A16-1)+(-F15)/E16,"") | H16: =Resultados!$E$38*$B16-Resultados!$F$38*$B16-Premissas!$B$24-Resultados!$E$38*$B16*(Premissas!$B$14/100) -> 24432.4 | I16: =H16-$C16 -> 24432.4 | J16: =J15+I16 -> -114252.12 | K16: =IF(AND(J15<0,J16>=0,A16<=MAX(120,Premissas!$B$15*12)),(A16-1)+(-J15)/I16,"") | L16: =Resultados!$E$39*$B16-Resultados!$F$39*$B16-Premissas!$B$24-Resultados!$E$39*$B16*(Premissas!$B$14/100) -> 29837.8 | M16: =L16-$C16 -> 29837.8 | N16: =N15+M16 -> -67225.14 | O16: =IF(AND(N15<0,N16>=0,A16<=MAX(120,Premissas!$B$15*12)),(A16-1)+(-N15)/M16,"") | P16: =Resultados!$B$19*$B16-Resultados!$B$20*$B16-Premissas!$B$24-Resultados!$B$19*$B16*(Premissas!$B$14/100) -> 24432.4 | Q16: =P16-$C16 -> 24432.4 | R16: =R15+Q16 -> -114252.12 | S16: =IF(AND(R15<0,R16>=0,A16<=MAX(120,Premissas!$B$15*12)),(A16-1)+(-R15)/Q16,"")
... A604: =A603+1 -> 600 | B604: =IF(Premissas!$B$9<=1,1,MIN(1,Premissas!$B$8/100+(1-Premissas!$B$8/100)*(A604-1)/(Premissas!$B$9-1))) -> 1 | C604: =IF(A604<=Resultados!$B$9,Resultados!$B$10,0) -> 0 | D604: =Resultados!$E$37*$B604-Resultados!$F$37*$B604-Premissas!$B$24-Resultados!$E$37*$B604*(Premissas!$B$14/100) -> 19027 | E604: =D604-$C604 -> 19027 | F604: =F603+E604 -> 11026597 | G604: =IF(AND(F603<0,F604>=0,A604<=MAX(120,Premissas!$B$15*12)),(A604-1)+(-F603)/E604,"") | H604: =Resultados!$E$38*$B604-Resultados!$F$38*$B604-Premissas!$B$24-Resultados!$E$38*$B604*(Premissas!$B$14/100) -> 24432.4 | I604: =H604-$C604 -> 24432.4 | J604: =J603+I604 -> 14251999 | K604: =IF(AND(J603<0,J604>=0,A604<=MAX(120,Premissas!$B$15*12)),(A604-1)+(-J603)/I604,"") | L604: =Resultados!$E$39*$B604-Resultados!$F$39*$B604-Premissas!$B$24-Resultados!$E$39*$B604*(Premissas!$B$14/100) -> 29837.8 | M604: =L604-$C604 -> 29837.8 | N604: =N603+M604 -> 17477401 | O604: =IF(AND(N603<0,N604>=0,A604<=MAX(120,Premissas!$B$15*12)),(A604-1)+(-N603)/M604,"") | P604: =Resultados!$B$19*$B604-Resultados!$B$20*$B604-Premissas!$B$24-Resultados!$B$19*$B604*(Premissas!$B$14/100) -> 24432.4 | Q604: =P604-$C604 -> 24432.4 | R604: =R603+Q604 -> 14251999 | S604: =IF(AND(R603<0,R604>=0,A604<=MAX(120,Premissas!$B$15*12)),(A604-1)+(-R603)/Q604,"")
